{
	"info": {
		"_postman_id": "37db2285-acf8-4f94-87b9-cb9162aabc21",
		"name": "Blog_Backend",
		"schema": "https://schema.getpostman.com/json/collection/v2.1.0/collection.json",
		"_exporter_id": "41656904"
	},
	"item": [
		{
			"name": "publications",
			"item": [
				{
					"name": "postPublication",
					"request": {
						"method": "POST",
						"header": [],
						"body": {
							"mode": "raw",
							"raw": "{\r\n    \"title\": \"Aviso!\",\r\n    \"description\": \"Hacer todas las tareas de los tres cursos jovénes!\",\r\n    \"course\": [\"TALLER III\", \"TECNOLOGÍA III\", \"PRÁCTICA SUPERVISADA\"]\r\n}",
							"options": {
								"raw": {
									"language": "json"
								}
							}
						},
						"url": {
							"raw": "http://localhost:3000/blog/v1/publications/postPublication",
							"protocol": "http",
							"host": [
								"localhost"
							],
							"port": "3000",
							"path": [
								"blog",
								"v1",
								"publications",
								"postPublication"
							]
						}
					},
					"response": []
				},
				{
					"name": "getPublications",
					"request": {
						"method": "GET",
						"header": [],
						"url": {
							"raw": "http://localhost:3000/blog/v1/publications/getPublications?limite=10&desde=0",
							"protocol": "http",
							"host": [
								"localhost"
							],
							"port": "3000",
							"path": [
								"blog",
								"v1",
								"publications",
								"getPublications"
							],
							"query": [
								{
									"key": "limite",
									"value": "10"
								},
								{
									"key": "desde",
									"value": "0"
								}
							]
						}
					},
					"response": []
				},
				{
					"name": "getPublicationById",
					"request": {
						"method": "GET",
						"header": [],
						"url": {
							"raw": "http://localhost:3000/blog/v1/publications/getPublicationById/68214af0647e137cc0492f4a",
							"protocol": "http",
							"host": [
								"localhost"
							],
							"port": "3000",
							"path": [
								"blog",
								"v1",
								"publications",
								"getPublicationById",
								"68214af0647e137cc0492f4a"
							]
						}
					},
					"response": []
				},
				{
					"name": "getPublicationsByCourseName",
					"request": {
						"method": "GET",
						"header": [],
						"url": {
							"raw": "http://localhost:3000/blog/v1/publications/getPublicationsByCourseName/TALLER III",
							"protocol": "http",
							"host": [
								"localhost"
							],
							"port": "3000",
							"path": [
								"blog",
								"v1",
								"publications",
								"getPublicationsByCourseName",
								"TALLER III"
							]
						}
					},
					"response": []
				},
				{
					"name": "getPublicationByTitle",
					"request": {
						"method": "GET",
						"header": [],
						"url": {
							"raw": "http://localhost:3000/blog/v1/publications/getPublicationByTitle/Evaluación final",
							"protocol": "http",
							"host": [
								"localhost"
							],
							"port": "3000",
							"path": [
								"blog",
								"v1",
								"publications",
								"getPublicationByTitle",
								"Evaluación final"
							]
						}
					},
					"response": []
				},
				{
					"name": "putPublication",
					"request": {
						"method": "PUT",
						"header": [],
						"body": {
							"mode": "raw",
							"raw": "{\r\n    \"title\": \"Evaluación final\",\r\n    \"description\": \"Se calificará con TECNOLOGÍA y TALLER\",\r\n    \"course\": [\"PRÁCTICA SUPERVISADA\"]\r\n}",
							"options": {
								"raw": {
									"language": "json"
								}
							}
						},
						"url": {
							"raw": "http://localhost:3000/blog/v1/publications/putPublication/68214af0647e137cc0492f4a",
							"protocol": "http",
							"host": [
								"localhost"
							],
							"port": "3000",
							"path": [
								"blog",
								"v1",
								"publications",
								"putPublication",
								"68214af0647e137cc0492f4a"
							]
						}
					},
					"response": []
				},
				{
					"name": "deletePublication",
					"request": {
						"method": "DELETE",
						"header": [],
						"url": {
							"raw": "http://localhost:3000/blog/v1/publications/deletePublication/6811072c9acec6c5dadac070",
							"protocol": "http",
							"host": [
								"localhost"
							],
							"port": "3000",
							"path": [
								"blog",
								"v1",
								"publications",
								"deletePublication",
								"6811072c9acec6c5dadac070"
							]
						}
					},
					"response": []
				}
			]
		},
		{
			"name": "courses",
			"item": [
				{
					"name": "postCourse",
					"request": {
						"method": "POST",
						"header": [],
						"body": {
							"mode": "raw",
							"raw": "{\r\n    \"name\": \"PRÁCTICA SUPERVISADA\"\r\n}",
							"options": {
								"raw": {
									"language": "json"
								}
							}
						},
						"url": {
							"raw": "http://localhost:3000/blog/v1/courses/postCourse",
							"protocol": "http",
							"host": [
								"localhost"
							],
							"port": "3000",
							"path": [
								"blog",
								"v1",
								"courses",
								"postCourse"
							]
						}
					},
					"response": []
				},
				{
					"name": "getCourses",
					"request": {
						"method": "GET",
						"header": [],
						"url": {
							"raw": "http://localhost:3000/blog/v1/courses/getCourses?limite=10&desde=0",
							"protocol": "http",
							"host": [
								"localhost"
							],
							"port": "3000",
							"path": [
								"blog",
								"v1",
								"courses",
								"getCourses"
							],
							"query": [
								{
									"key": "limite",
									"value": "10"
								},
								{
									"key": "desde",
									"value": "0"
								}
							]
						}
					},
					"response": []
				},
				{
					"name": "getCourseById",
					"request": {
						"method": "GET",
						"header": [],
						"url": {
							"raw": "http://localhost:3000/blog/v1/courses/getCourseById/68117446609be9078c36d8fb",
							"protocol": "http",
							"host": [
								"localhost"
							],
							"port": "3000",
							"path": [
								"blog",
								"v1",
								"courses",
								"getCourseById",
								"68117446609be9078c36d8fb"
							]
						}
					},
					"response": []
				},
				{
					"name": "getCourseByName",
					"request": {
						"method": "GET",
						"header": [],
						"url": {
							"raw": "http://localhost:3000/blog/v1/courses/getCourseByName/Lengua y Literatura",
							"protocol": "http",
							"host": [
								"localhost"
							],
							"port": "3000",
							"path": [
								"blog",
								"v1",
								"courses",
								"getCourseByName",
								"Lengua y Literatura"
							]
						}
					},
					"response": []
				},
				{
					"name": "putCourse",
					"request": {
						"method": "PUT",
						"header": [],
						"body": {
							"mode": "raw",
							"raw": "{\r\n    \"name\": \"Curso de Ejemplo update\"\r\n}",
							"options": {
								"raw": {
									"language": "json"
								}
							}
						},
						"url": {
							"raw": "http://localhost:3000/blog/v1/courses/putCourse/6811742a609be9078c36d8f9",
							"protocol": "http",
							"host": [
								"localhost"
							],
							"port": "3000",
							"path": [
								"blog",
								"v1",
								"courses",
								"putCourse",
								"6811742a609be9078c36d8f9"
							]
						}
					},
					"response": []
				},
				{
					"name": "deleteCourse",
					"request": {
						"method": "DELETE",
						"header": [],
						"url": {
							"raw": "http://localhost:3000/blog/v1/courses/deleteCourse/6811742a609be9078c36d8f9",
							"protocol": "http",
							"host": [
								"localhost"
							],
							"port": "3000",
							"path": [
								"blog",
								"v1",
								"courses",
								"deleteCourse",
								"6811742a609be9078c36d8f9"
							]
						}
					},
					"response": []
				}
			]
		},
		{
			"name": "comments",
			"item": [
				{
					"name": "postComment",
					"request": {
						"method": "POST",
						"header": [],
						"body": {
							"mode": "raw",
							"raw": "{\r\n    \"author\": \"Alex\",\r\n    \"comment\": \"Ya no quiero :(\",\r\n    \"publication\": \"Blog\"\r\n}",
							"options": {
								"raw": {
									"language": "json"
								}
							}
						},
						"url": {
							"raw": "http://localhost:3000/blog/v1/comments/postComment",
							"protocol": "http",
							"host": [
								"localhost"
							],
							"port": "3000",
							"path": [
								"blog",
								"v1",
								"comments",
								"postComment"
							]
						}
					},
					"response": []
				},
				{
					"name": "getComments",
					"request": {
						"method": "GET",
						"header": [],
						"url": {
							"raw": "http://localhost:3000/blog/v1/comments/getComments?limite=10&desde=0",
							"protocol": "http",
							"host": [
								"localhost"
							],
							"port": "3000",
							"path": [
								"blog",
								"v1",
								"comments",
								"getComments"
							],
							"query": [
								{
									"key": "limite",
									"value": "10"
								},
								{
									"key": "desde",
									"value": "0"
								}
							]
						}
					},
					"response": []
				},
				{
					"name": "getCommentById",
					"request": {
						"method": "GET",
						"header": [],
						"url": {
							"raw": "http://localhost:3000/blog/v1/comments/getCommentById/682152cf103f30cd7a46284c",
							"protocol": "http",
							"host": [
								"localhost"
							],
							"port": "3000",
							"path": [
								"blog",
								"v1",
								"comments",
								"getCommentById",
								"682152cf103f30cd7a46284c"
							]
						}
					},
					"response": []
				},
				{
					"name": "getCommentByPublication",
					"request": {
						"method": "GET",
						"header": [],
						"url": {
							"raw": "http://localhost:3000/blog/v1/comments/getCommentByPublication/Blog",
							"protocol": "http",
							"host": [
								"localhost"
							],
							"port": "3000",
							"path": [
								"blog",
								"v1",
								"comments",
								"getCommentByPublication",
								"Blog"
							]
						}
					},
					"response": []
				},
				{
					"name": "putComment",
					"request": {
						"method": "PUT",
						"header": [],
						"body": {
							"mode": "raw",
							"raw": "{\r\n    \"author\": \"Alex\",\r\n    \"comment\": \"Ya no quiero gg\",\r\n    \"publication\": \"Blog\"\r\n}",
							"options": {
								"raw": {
									"language": "json"
								}
							}
						},
						"url": {
							"raw": "http://localhost:3000/blog/v1/comments/putComment/682152cf103f30cd7a46284c",
							"protocol": "http",
							"host": [
								"localhost"
							],
							"port": "3000",
							"path": [
								"blog",
								"v1",
								"comments",
								"putComment",
								"682152cf103f30cd7a46284c"
							]
						}
					},
					"response": []
				},
				{
					"name": "deleteComment",
					"request": {
						"method": "DELETE",
						"header": [],
						"url": {
							"raw": "http://localhost:3000/blog/v1/comments/deleteComment/681259fbc4b27cec07409422",
							"protocol": "http",
							"host": [
								"localhost"
							],
							"port": "3000",
							"path": [
								"blog",
								"v1",
								"comments",
								"deleteComment",
								"681259fbc4b27cec07409422"
							]
						}
					},
					"response": []
				}
			]
		}
	]
}